llmap/__init__.py
llmap/ai.py
llmap/cache.py
llmap/exceptions.py
llmap/llmap.py
llmap/parse.py
llmap/deepseek_v3_tokenizer/__init__.py
llmap/deepseek_v3_tokenizer/tokenizer.json
llmap/deepseek_v3_tokenizer/tokenizer_config.json
llmap/queries/c_sharp/skeleton.scm
llmap/queries/java/skeleton.scm
llmap/queries/python/skeleton.scm
llmap_ai-1.0.0.dist-info/LICENSE.txt
llmap_ai-1.0.0.dist-info/METADATA
llmap_ai-1.0.0.dist-info/WHEEL
llmap_ai-1.0.0.dist-info/entry_points.txt
llmap_ai-1.0.0.dist-info/top_level.txt
llmap_ai-1.0.0.dist-info/RECORD
