Metadata-Version: 2.2
Name: llmap-ai
Version: 1.0.0
Summary: High performance code search for large codebases
Author-email: Jonathan Ellis <jbellis@gmail.com>
Project-URL: Homepage, https://github.com/jbellis/llmap
Project-URL: Issues, https://github.com/jbellis/llmap/issues
Classifier: Programming Language :: Python :: 3
Classifier: License :: OSI Approved :: Apache Software License
Classifier: Operating System :: OS Independent
Requires-Python: >=3.10
License-File: LICENSE.txt
Requires-Dist: openai<2.0.0,>=1.58.1
Requires-Dist: transformers>=4.47.1
Requires-Dist: tree-sitter==0.21.3
Requires-Dist: tree-sitter-languages==1.10.2
Requires-Dist: tree-sitter-c-sharp
Requires-Dist: tqdm
